{
    "configurations": [
        {
            "name": "Win32",
            "includePath": [
                "${workspaceFolder}/**",
                "${vcpkgRoot}/x86-windows/include"
            ],
            "defines": [
                "_DEBUG",
                "UNICODE",
                "_UNICODE"
            ],
            "windowsSdkVersion": "10.0.19041.0",
            "cStandard": "c17",
            "cppStandard": "c++23",
            "compilerArgs": [
                "-lopengl32",
                "-lglu32",
                "-lfreeglut"
            ],
            "compilerPath": "C:/msys64/mingw64/bin/g++.exe",
            "intelliSenseMode": "gcc-x64"
        }
    ],
    "version": 4
}